{
  "tasks": [
    {
      "id": "t-vr01",
      "title": "Připravit otázky k ukončení Azmed; naplánovat termination meeting",
      "owner": "Marie",
      "deadline": "",
      "priority": "high",
      "done": false,
      "createdAt": "2026-03-26T09:00:00Z",
      "createdInReport": "2026-03-26",
      "completedAt": null,
      "notes": "Do příštího callu"
    },
    {
      "id": "t-vr02",
      "title": "Sestavit seznam potenciálních polských distributorů",
      "owner": "Marie",
      "deadline": "",
      "priority": "high",
      "done": false,
      "createdAt": "2026-03-26T09:00:00Z",
      "createdInReport": "2026-03-26",
      "completedAt": null,
      "notes": "Co nejdříve"
    },
    {
      "id": "t-vr04",
      "title": "Odeslat odkaz na certifikační disk USA partnerovi + checklist dokumentace",
      "owner": "Marie/Jana",
      "deadline": "",
      "priority": "high",
      "done": false,
      "createdAt": "2026-03-26T09:00:00Z",
      "createdInReport": "2026-03-26",
      "completedAt": null,
      "notes": "Co nejdříve"
    },
    {
      "id": "t-vr05",
      "title": "Připravit plán USA distributora (včetně Minnesota-only varianty)",
      "owner": "Jana",
      "deadline": "",
      "priority": "medium",
      "done": false,
      "createdAt": "2026-03-26T09:00:00Z",
      "createdInReport": "2026-03-26",
      "completedAt": null,
      "notes": "Rozpracovat"
    },
    {
      "id": "t-vr06",
      "title": "Získat nahrávky přednášek Milana Šemíka; sdílet s týmem",
      "owner": "Aleš",
      "deadline": "",
      "priority": "medium",
      "done": false,
      "createdAt": "2026-03-26T09:00:00Z",
      "createdInReport": "2026-03-26",
      "completedAt": null,
      "notes": "Čeká na Šemíka"
    }
  ]
}